hastebin_client
