Metadata-Version: 1.1
Name: hastebin-client
Version: 0.1.2
Summary: Command line tool for uploading files to hastebin.com
Home-page: https://github.com/RobertKolner/hastebin-client
Author: Robert Kolner
Author-email: robert.kolner@gmail.com
License: MIT
Download-URL: https://github.com/RobertKolner/hastebin-client/releases/tag/0.1.1
Keywords: hastebin,haste,client
Platform: UNKNOWN
